netbox_device_view/__init__.py
netbox_device_view/filtersets.py
netbox_device_view/forms.py
netbox_device_view/models.py
netbox_device_view/navigation.py
netbox_device_view/tables.py
netbox_device_view/template_content.py
netbox_device_view/urls.py
netbox_device_view/utils.py
netbox_device_view/views.py
netbox_device_view/api/__init__.py
netbox_device_view/api/serializers.py
netbox_device_view/api/urls.py
netbox_device_view/api/views.py
netbox_device_view/migrations/0001_initial.py
netbox_device_view/migrations/__init__.py
netbox_device_view/static/netbox_device_view/css/device_view.css
netbox_device_view/templates/netbox_device_view/deviceview.html
netbox_device_view/templates/netbox_device_view/ports.html
netbox_device_view-0.1.7.dist-info/METADATA
netbox_device_view-0.1.7.dist-info/WHEEL
netbox_device_view-0.1.7.dist-info/top_level.txt
netbox_device_view-0.1.7.dist-info/RECORD
