Metadata-Version: 2.1
Name: netbox-device-view
Version: 0.1.7
Summary: NetBox Device View plugin
Home-page: https://github.com/peterbaumert/netbox-device-view
Author: Peter Baumert
Keywords: netbox,netbox-plugin
Classifier: Framework :: Django
Classifier: Programming Language :: Python :: 3
